Workbook

Sheet Lisez-moi
A1: PACK COMITÉ — FONDS CORE+ FRANCE (FICTIF)
A2: Situation au 31/03/2026 · généré automatiquement depuis le data model du cockpit (data.js)
A4: Ce classeur reproduit, en formules Excel auditables, le moteur de calcul du cockpit web :
A5: · Grille actifs — inputs par actif ; LTV et contrôle NOI ÷ cap en formules
A6: · Dette & couverture — exposition nette, service, écarts vs BP en formules
A7: · Agrégats & covenants — GAV, NAV, VL, DSCR, ratios : aucune valeur saisie, tout est dérivé
A8: · Scénario Bear — hypothèses paramétrables (loyers −10 %, vacance +400 bps, caps +125 bps, taux +150 bps)
A9: · Contrôles — recette PASS / FAIL comparant le classeur aux valeurs de référence du cockpit
A11: Code couleur : BLEU = input modifiable · NOIR = formule · VERT = lien inter-onglets
A13: Sources de marché : JLL Research, Investment I&L France Q1 2026 ; JLL Research, Investment Greater Paris Region Q1 2026.
A14: Fonds fictif à but de démonstration. Cap rates ancrés sur les notes JLL France Q1 2026 (I&L et Greater Paris Region) ; les niveaux par actif sont des hypothèses calibrées, non une base de marché propriétaire.

Sheet Grille actifs
A1: ID | B1: Actif | C1: Type | D1: Profil | E1: Localisation | F1: Occupation | G1: WAULT (ans) | H1: Index | I1: Valeur (€m) | J1: Cap rate | K1: NOI (€m) | L1: Dette (€m) | M1: LTV actif | N1: NOI ÷ cap (€m) | O1: Écart check (€m)
A2: A1 | B2: Bureau Paris QCA | C2: Bureau | D2: Core+ | E2: Paris 8e | F2: 0.97 | G2: 5.2 | H2: ILAT | I2: 94 | J2: 0.0425 | K2: 4 | L2: 42 | M2: =L2/I2 | N2: =K2/J2 | O2: =I2-N2
A3: A2 | B3: Tour La Défense | C3: Bureau | D3: Value-add | E3: Courbevoie | F3: 0.83 | G3: 3.1 | H3: ILAT | I3: 50.4 | J3: 0.075 | K3: 3.78 | L3: 31 | M3: =L3/I3 | N3: =K3/J3 | O3: =I3-N3
A4: A3 | B4: Plateforme logistique | C4: Logistique | D4: Core+ | E4: Corridor Lyon–Marseille | F4: 0.98 | G4: 6.8 | H4: ILAT | I4: 70 | J4: 0.051 | K4: 3.57 | L4: 32 | M4: =L4/I4 | N4: =K4/J4 | O4: =I4-N4
A5: A4 | B5: Retail park | C5: Commerce | D5: Income / secondaire | E5: Périphérie Lille | F5: 0.92 | G5: 4 | H5: ILC | I5: 39 | J5: 0.069 | K5: 2.69 | L5: 18 | M5: =L5/I5 | N5: =K5/J5 | O5: =I5-N5
A6: A5 | B6: Résidentiel géré | C6: Résidentiel | D6: Défensif | E6: Île-de-France | F6: 0.95 | G6: n.a. | H6: IRL | I6: 35 | J6: 0.044 | K6: 1.54 | L6: 14 | M6: =L6/I6 | N6: =K6/J6 | O6: =I6-N6
A7: A6 | B7: Bureau Part-Dieu | C7: Bureau | D7: Core+ régional | E7: Lyon 3e | F7: 0.94 | G7: 4.6 | H7: ILAT | I7: 29 | J7: 0.055 | K7: 1.6 | L7: 12 | M7: =L7/I7 | N7: =K7/J7 | O7: =I7-N7
B8: Portefeuille (6 actifs) | I8: =SUM(I2:I7) | J8: =K8/I8 | K8: =SUM(K2:K7) | L8: =SUM(L2:L7) | M8: =L8/I8
A10: Convention : la Valeur est la donnée d'expertise (suivi en appui du valorisateur indépendant) ; NOI ÷ cap est le contrôle de cohérence (tolérance €0,2m, cf. onglet Contrôles).

Sheet Dette & couverture
A1: ID | B1: Taux all-in | C1: Part variable | D1: Couverture | E1: Expo nette (€m) | F1: Service (€m) | G1: Capex / TI (€m) | H1: BP NOI (€m) | I1: Écart NOI vs BP
A2: A1 | B2: 0.042 | C2: 0.35 | D2: 0.5 | E2: ='Grille actifs'!L2*C2*(1-D2) | F2: ='Grille actifs'!L2*B2 | G2: 0.35 | H2: 4.1 | I2: ='Grille actifs'!K2/H2-1
A3: A2 | B3: 0.0485 | C3: 0.65 | D3: 0.25 | E3: ='Grille actifs'!L3*C3*(1-D3) | F3: ='Grille actifs'!L3*B3 | G3: 0.95 | H3: 4.2 | I3: ='Grille actifs'!K3/H3-1
A4: A3 | B4: 0.0405 | C4: 0.3 | D4: 0.6 | E4: ='Grille actifs'!L4*C4*(1-D4) | F4: ='Grille actifs'!L4*B4 | G4: 0.25 | H4: 3.6 | I4: ='Grille actifs'!K4/H4-1
A5: A4 | B5: 0.051 | C5: 0.45 | D5: 0.3 | E5: ='Grille actifs'!L5*C5*(1-D5) | F5: ='Grille actifs'!L5*B5 | G5: 0.3 | H5: 2.75 | I5: ='Grille actifs'!K5/H5-1
A6: A5 | B6: 0.0435 | C6: 0.3 | D6: 0.5 | E6: ='Grille actifs'!L6*C6*(1-D6) | F6: ='Grille actifs'!L6*B6 | G6: 0.22 | H6: 1.5 | I6: ='Grille actifs'!K6/H6-1
A7: A6 | B7: 0.0455 | C7: 0.4 | D7: 0.4 | E7: ='Grille actifs'!L7*C7*(1-D7) | F7: ='Grille actifs'!L7*B7 | G7: 0.28 | H7: 1.65 | I7: ='Grille actifs'!K7/H7-1
A8: Total | E8: =SUM(E2:E7) | F8: =SUM(F2:F7) | G8: =SUM(G2:G7) | H8: =SUM(H2:H7) | I8: ='Grille actifs'!K8/H8-1
A10: Expo nette = dette × part variable × (1 − couverture) : seule assiette sensible à la hausse des taux. Service = dette × taux all-in (interest-only).

Sheet Agrégats & covenants
A1: AGRÉGATS DU FONDS — aucun chiffre saisi, tout est dérivé des onglets sources
A3: GAV (€m) | B3: ='Grille actifs'!I8
A4: NOI total (€m) | B4: ='Grille actifs'!K8
A5: Cap rate blended | B5: =B4/B3
A6: Dette totale (€m) | B6: ='Grille actifs'!L8
A7: LTV consolidée | B7: =B6/B3
A8: Cash (€m) | B8: 8.2
A9: Autres passifs (€m) | B9: 6.1
A10: NAV (€m) | B10: =B3-B6+B8-B9
A11: Nombre de parts | B11: 1705000
A12: VL par part (€) | B12: =B10*1000000/B11
A14: Service de dette (€m) | B14: ='Dette & couverture'!F8
A15: DSCR covenant (interest-only) | B15: =B4/B14
A16: Capex / TI total (€m) | B16: ='Dette & couverture'!G8
A17: Cash-flow après capex (€m) | B17: =B4-B16
A18: DSCR après capex / TI | B18: =B17/B14
A19: Exposition nette taux (€m) | B19: ='Dette & couverture'!E8
A21: COVENANTS & RATIOS DE STRUCTURE
A22: Covenant LTV max | B22: 0.6
A23: Seuil d'alerte LTV | B23: 0.57
A24: Statut LTV | B24: =IF(B7>B22,"BREACH",IF(B7>=B23,"ALERTE","CONFORME"))
A25: Covenant DSCR min | B25: 1.2
A26: Statut DSCR | B26: =IF(B15<B25,"BREACH","CONFORME")
A27: Ratio d'emprise max (1er actif / GAV) | B27: =MAX('Grille actifs'!I2:I7)/B3
A28: Limite interne d'emprise | B28: 0.35
A29: Statut emprise | B29: =IF(B27>B28,"DÉPASSEMENT","CONFORME")
A30: Levier AIFM simplifié (GAV / NAV) | B30: =B3/B10
A31: Plafond prospectus | B31: 2.5
A32: Statut levier | B32: =IF(B30>B31,"DÉPASSEMENT","CONFORME")
A33: LTV nette de trésorerie | B33: =(B6-B8)/B3

Sheet Scénario Bear
A1: SCÉNARIO BEAR — hypothèses modifiables (bleu), tout le reste recalcule
A2: Choc sur les loyers | B2: -0.1
A3: Vacance additionnelle | B3: 0.04
A4: Expansion des cap rates | B4: 0.0125
A5: Hausse des taux courts | B5: 0.015
A8: ID | B8: NOI stressé (€m) | C8: Cap stressé | D8: Valeur stressée (€m) | E8: Dette (€m) | F8: LTV actif
A9: A1 | B9: ='Grille actifs'!K2*(1+$B$2)*(1-$B$3) | C9: ='Grille actifs'!J2+$B$4 | D9: =B9/C9 | E9: ='Grille actifs'!L2 | F9: =E9/D9
A10: A2 | B10: ='Grille actifs'!K3*(1+$B$2)*(1-$B$3) | C10: ='Grille actifs'!J3+$B$4 | D10: =B10/C10 | E10: ='Grille actifs'!L3 | F10: =E10/D10
A11: A3 | B11: ='Grille actifs'!K4*(1+$B$2)*(1-$B$3) | C11: ='Grille actifs'!J4+$B$4 | D11: =B11/C11 | E11: ='Grille actifs'!L4 | F11: =E11/D11
A12: A4 | B12: ='Grille actifs'!K5*(1+$B$2)*(1-$B$3) | C12: ='Grille actifs'!J5+$B$4 | D12: =B12/C12 | E12: ='Grille actifs'!L5 | F12: =E12/D12
A13: A5 | B13: ='Grille actifs'!K6*(1+$B$2)*(1-$B$3) | C13: ='Grille actifs'!J6+$B$4 | D13: =B13/C13 | E13: ='Grille actifs'!L6 | F13: =E13/D13
A14: A6 | B14: ='Grille actifs'!K7*(1+$B$2)*(1-$B$3) | C14: ='Grille actifs'!J7+$B$4 | D14: =B14/C14 | E14: ='Grille actifs'!L7 | F14: =E14/D14
A15: Total | B15: =SUM(B9:B14) | D15: =SUM(D9:D14) | E15: =SUM(E9:E14) | F15: =E15/D15
A17: Service de dette stressé (€m) | B17: ='Dette & couverture'!F8+$B$5*'Dette & couverture'!E8
A18: DSCR covenant (IO) | B18: =B15/B17
A19: DSCR après capex / TI | B19: =(B15-'Dette & couverture'!G8)/B17
A20: NAV stressée (€m) | B20: =D15-E15+'Agrégats & covenants'!B8-'Agrégats & covenants'!B9
A21: VL stressée (€) | B21: =B20*1000000/'Agrégats & covenants'!B11
A22: Statut covenant LTV | B22: =IF(F15>'Agrégats & covenants'!B22,"BREACH",IF(F15>='Agrégats & covenants'!B23,"ALERTE","CONFORME"))
A23: Statut covenant DSCR | B23: =IF(B18<'Agrégats & covenants'!B25,"BREACH","CONFORME")
A25: Lecture : la LTV casse (canal valeur), le DSCR tient (dette interest-only + couverture de taux). Les deux DSCR dérivent du même NOI stressé.

Sheet Contrôles
A1: Contrôle | B1: Valeur du classeur | C1: Référence cockpit | D1: Tolérance | E1: Statut
A2: GAV (€m) | B2: ='Agrégats & covenants'!B3 | C2: 317.4 | D2: 0.05 | E2: =IF(ABS(B2-C2)<=D2,"PASS","FAIL")
A3: NOI total (€m) | B3: ='Agrégats & covenants'!B4 | C3: 17.18 | D3: 0.005 | E3: =IF(ABS(B3-C3)<=D3,"PASS","FAIL")
A4: Dette totale (€m) | B4: ='Agrégats & covenants'!B6 | C4: 149 | D4: 0.001 | E4: =IF(ABS(B4-C4)<=D4,"PASS","FAIL")
A5: LTV consolidée | B5: ='Agrégats & covenants'!B7 | C5: 0.46944 | D5: 0.0005 | E5: =IF(ABS(B5-C5)<=D5,"PASS","FAIL")
A6: NAV (€m) | B6: ='Agrégats & covenants'!B10 | C6: 170.5 | D6: 0.05 | E6: =IF(ABS(B6-C6)<=D6,"PASS","FAIL")
A7: VL par part (€) | B7: ='Agrégats & covenants'!B12 | C7: 100 | D7: 0.01 | E7: =IF(ABS(B7-C7)<=D7,"PASS","FAIL")
A8: DSCR covenant (IO) | B8: ='Agrégats & covenants'!B15 | C8: 2.5887 | D8: 0.005 | E8: =IF(ABS(B8-C8)<=D8,"PASS","FAIL")
A9: DSCR après capex / TI | B9: ='Agrégats & covenants'!B18 | C9: 2.2346 | D9: 0.005 | E9: =IF(ABS(B9-C9)<=D9,"PASS","FAIL")
A10: Exposition nette taux (€m) | B10: ='Agrégats & covenants'!B19 | C10: 36.95 | D10: 0.01 | E10: =IF(ABS(B10-C10)<=D10,"PASS","FAIL")
A11: Écart max valeur vs NOI÷cap (€m) | B11: =MAX(MAX('Grille actifs'!O2:O7),-MIN('Grille actifs'!O2:O7)) | C11: 0 | D11: 0.2 | E11: =IF(ABS(B11-C11)<=D11,"PASS","FAIL")
A12: Bear — GAV stressée (€m) | B12: ='Scénario Bear'!D15 | C12: 221.28 | D12: 0.05 | E12: =IF(ABS(B12-C12)<=D12,"PASS","FAIL")
A13: Bear — LTV consolidée | B13: ='Scénario Bear'!F15 | C13: 0.67335 | D13: 0.001 | E13: =IF(ABS(B13-C13)<=D13,"PASS","FAIL")
A14: Bear — DSCR covenant | B14: ='Scénario Bear'!B18 | C14: 2.0642 | D14: 0.005 | E14: =IF(ABS(B14-C14)<=D14,"PASS","FAIL")
A15: Bear — DSCR après capex | B15: ='Scénario Bear'!B19 | C15: 1.7375 | D15: 0.005 | E15: =IF(ABS(B15-C15)<=D15,"PASS","FAIL")
A17: Synthèse | E17: =IF(COUNTIF(E2:E15,"FAIL")=0,"✓ TOUS LES CONTRÔLES PASSENT",COUNTIF(E2:E15,"FAIL")&" ÉCHEC(S)")
A19: Références = valeurs de la recette automatique du cockpit (12/12 tests). Si un input change, les statuts basculent en FAIL tant que la référence n'est pas réalignée.
